obse/__init__.py
obse/graphwrapper.py
obse/namespace.py
obse/ontologyresolver.py
obse/sparql_queries.py
obse/statemachine.ttl
obse-1.2.0.dist-info/LICENSE
obse-1.2.0.dist-info/METADATA
obse-1.2.0.dist-info/WHEEL
obse-1.2.0.dist-info/top_level.txt
obse-1.2.0.dist-info/RECORD
